Workbook

Sheet Model
B1: GlowNest — Dynamic Profitability Model | E1: Blue = editable input | Black = formula
B3: INPUTS (edit the yellow cells) | E3: LIVE HEALTH CHECK
B4: Selling Price (SP) | C4: 800 | E4: =IF($C$19<0,"🔴 LOSS-MAKING — profit is negative",IF($C$21>0.15,"🟡 WATCH — TACOS above 15%","🟢 HEALTHY — profitable & TACOS under 15%")) -> 🟢 HEALTHY — profitable & TACOS under 15%
B5: COGS | C5: 280
B6: Amazon Referral Fee (%) | C6: 0.12
B7: Monthly Ad Spend | C7: 300000 | E7: Guide rails:
B8: Units Sold via Ads | C8: 1500 | E8: • Profit < 0 → red flag, cut spend or fix efficiency
B9: Organic Units Sold | C9: 2000 | E9: • TACOS > 15% → yellow, ad-dependence rising
B10: Fixed Costs (monthly) | C10: 150000 | E10: • TACOS falling with flat spend → organic compounding (good)
B12: OUTPUTS (auto-calculated)
B13: Gross Margin per Unit | C13: =$C$4-$C$5 -> 520
B14: Amazon Fee per Unit | C14: =$C$4*$C$6 -> 96
B15: Ad Cost per Unit | C15: =$C$7/$C$8 -> 200
B16: Net Margin – Ad Units | C16: =$C$13-$C$14-$C$15 -> 224
B17: Net Margin – Organic Units | C17: =$C$13-$C$14 -> 424
B18: Total Monthly Revenue | C18: =$C$4*($C$8+$C$9) -> 2800000
B19: Total Monthly Profit | C19: =($C$16*$C$8)+($C$17*$C$9)-$C$10 -> 1034000
B20: ACOS | C20: =$C$7/($C$4*$C$8) -> 0.25
B21: TACOS | C21: =$C$7/$C$18 -> 0.10714286
B22: Break-Even Ad Spend | C22: =($C$17*$C$8)+($C$17*$C$9)-$C$10 -> 1334000
B24: Break-Even Ad Spend = the max ad spend before profit hits ₹0, holding ad-units constant. It equals total contribution margin (net margin × all units) minus fixed costs. Beyond this point each extra rupee of ad spend is unprofitable at current efficiency.

Sheet Sensitivity
A1: Ad-Spend Sensitivity (holding ad-units at current input)
A3: Ad Spend (₹) | B3: Profit (₹) | C3: TACOS
A4: 0 | B4: =((Model!$C$4-Model!$C$5)-(Model!$C$4*Model!$C$6))*Model!$C$8 - A4 + ((Model!$C$4-Model!$C$5)-(Model!$C$4*Model!$C$6))*Model!$C$9 - Model!$C$10 -> 1334000 | C4: =A4/(Model!$C$4*(Model!$C$8+Model!$C$9)) -> 0
A5: 100000 | B5: =((Model!$C$4-Model!$C$5)-(Model!$C$4*Model!$C$6))*Model!$C$8 - A5 + ((Model!$C$4-Model!$C$5)-(Model!$C$4*Model!$C$6))*Model!$C$9 - Model!$C$10 -> 1234000 | C5: =A5/(Model!$C$4*(Model!$C$8+Model!$C$9)) -> 0.035714286
A6: 200000 | B6: =((Model!$C$4-Model!$C$5)-(Model!$C$4*Model!$C$6))*Model!$C$8 - A6 + ((Model!$C$4-Model!$C$5)-(Model!$C$4*Model!$C$6))*Model!$C$9 - Model!$C$10 -> 1134000 | C6: =A6/(Model!$C$4*(Model!$C$8+Model!$C$9)) -> 0.071428571
A7: 300000 | B7: =((Model!$C$4-Model!$C$5)-(Model!$C$4*Model!$C$6))*Model!$C$8 - A7 + ((Model!$C$4-Model!$C$5)-(Model!$C$4*Model!$C$6))*Model!$C$9 - Model!$C$10 -> 1034000 | C7: =A7/(Model!$C$4*(Model!$C$8+Model!$C$9)) -> 0.10714286
A8: 400000 | B8: =((Model!$C$4-Model!$C$5)-(Model!$C$4*Model!$C$6))*Model!$C$8 - A8 + ((Model!$C$4-Model!$C$5)-(Model!$C$4*Model!$C$6))*Model!$C$9 - Model!$C$10 -> 934000 | C8: =A8/(Model!$C$4*(Model!$C$8+Model!$C$9)) -> 0.14285714
A9: 500000 | B9: =((Model!$C$4-Model!$C$5)-(Model!$C$4*Model!$C$6))*Model!$C$8 - A9 + ((Model!$C$4-Model!$C$5)-(Model!$C$4*Model!$C$6))*Model!$C$9 - Model!$C$10 -> 834000 | C9: =A9/(Model!$C$4*(Model!$C$8+Model!$C$9)) -> 0.17857143
A10: 600000 | B10: =((Model!$C$4-Model!$C$5)-(Model!$C$4*Model!$C$6))*Model!$C$8 - A10 + ((Model!$C$4-Model!$C$5)-(Model!$C$4*Model!$C$6))*Model!$C$9 - Model!$C$10 -> 734000 | C10: =A10/(Model!$C$4*(Model!$C$8+Model!$C$9)) -> 0.21428571
A11: 700000 | B11: =((Model!$C$4-Model!$C$5)-(Model!$C$4*Model!$C$6))*Model!$C$8 - A11 + ((Model!$C$4-Model!$C$5)-(Model!$C$4*Model!$C$6))*Model!$C$9 - Model!$C$10 -> 634000 | C11: =A11/(Model!$C$4*(Model!$C$8+Model!$C$9)) -> 0.25
A12: 800000 | B12: =((Model!$C$4-Model!$C$5)-(Model!$C$4*Model!$C$6))*Model!$C$8 - A12 + ((Model!$C$4-Model!$C$5)-(Model!$C$4*Model!$C$6))*Model!$C$9 - Model!$C$10 -> 534000 | C12: =A12/(Model!$C$4*(Model!$C$8+Model!$C$9)) -> 0.28571429
A13: 900000 | B13: =((Model!$C$4-Model!$C$5)-(Model!$C$4*Model!$C$6))*Model!$C$8 - A13 + ((Model!$C$4-Model!$C$5)-(Model!$C$4*Model!$C$6))*Model!$C$9 - Model!$C$10 -> 434000 | C13: =A13/(Model!$C$4*(Model!$C$8+Model!$C$9)) -> 0.32142857
A14: 1000000 | B14: =((Model!$C$4-Model!$C$5)-(Model!$C$4*Model!$C$6))*Model!$C$8 - A14 + ((Model!$C$4-Model!$C$5)-(Model!$C$4*Model!$C$6))*Model!$C$9 - Model!$C$10 -> 334000 | C14: =A14/(Model!$C$4*(Model!$C$8+Model!$C$9)) -> 0.35714286
A15: 1100000 | B15: =((Model!$C$4-Model!$C$5)-(Model!$C$4*Model!$C$6))*Model!$C$8 - A15 + ((Model!$C$4-Model!$C$5)-(Model!$C$4*Model!$C$6))*Model!$C$9 - Model!$C$10 -> 234000 | C15: =A15/(Model!$C$4*(Model!$C$8+Model!$C$9)) -> 0.39285714
... A17: 1300000 | B17: =((Model!$C$4-Model!$C$5)-(Model!$C$4*Model!$C$6))*Model!$C$8 - A17 + ((Model!$C$4-Model!$C$5)-(Model!$C$4*Model!$C$6))*Model!$C$9 - Model!$C$10 -> 34000 | C17: =A17/(Model!$C$4*(Model!$C$8+Model!$C$9)) -> 0.46428571

Sheet Scenarios
B1: Scenario Analysis (Task 2)
B3: Scenario | C3: Key change | D3: Profit | E3: TACOS | F3: Takeaway
B4: 1. Price ↑ to ₹950 | C4: SP 800→950 | D4: ₹14,96,000 | E4: 9.0% | F4: Profit +₹4.62L; TACOS falls (higher revenue base). Pricing power is the strongest lever.
B5: 2. COGS +20% | C5: COGS 280→336 | D5: — | E5: — | F5: Break-even ad spend drops 800→₹11.38L (from ₹13.34L). Cost inflation shrinks the cushion.
B6: 3. Organic ↑ to 3,500 | C6: Organic 2000→3500 | D6: ₹17,98,000 | E6: 7.5% | F6: TACOS falls 10.7%→7.5% with SAME spend. Organic growth = the health metric improving for free.
B7: 4. Price war: SP ₹700 | C7: SP 800→700 | D7: ₹7,26,000 | E7: 13.4% | F7: Net margin/ad-unit 224→136. Still profitable but margin nearly halves. Compete on value, not price.
B9: Note: figures computed from the Model logic. To reproduce live, change the matching blue input on the Model sheet and read Total Monthly Profit / TACOS. Scenario 2 break-even is read from the Break-Even Ad Spend output.
